irisclient/__init__.py
irisclient/compat.py
irisclient/exceptions.py
irisclient-1.3.0.dist-info/LICENSE
irisclient-1.3.0.dist-info/METADATA
irisclient-1.3.0.dist-info/WHEEL
irisclient-1.3.0.dist-info/top_level.txt
irisclient-1.3.0.dist-info/RECORD
