Metadata-Version: 2.1
Name: irisclient
Version: 1.3.0
Summary: Python client for Iris API
Home-page: https://github.com/houqp/iris-python-client
Author: Minhaz Mahmud
Author-email: UNKNOWN
License: BSD 2-CLAUSE
Platform: UNKNOWN
Classifier: Development Status :: 5 - Production/Stable
Classifier: Intended Audience :: Developers
Classifier: Natural Language :: English
Classifier: Programming Language :: Python
Classifier: Programming Language :: Python :: 2.6
Classifier: Programming Language :: Python :: 2.7
Classifier: Programming Language :: Python :: 3.3
Classifier: Programming Language :: Python :: 3.4
Classifier: Programming Language :: Python :: 3.5
Classifier: Programming Language :: Python :: 3.6
Classifier: Programming Language :: Python :: Implementation :: CPython
Requires-Dist: requests
